scouter/Scouter.py
scouter/ScouterData.py
scouter/__init__.py
scouter/_datasets.py
scouter/_model.py
scouter/_utils.py
scouter/_version.py
scouter_learn-0.1.10.dist-info/LICENSE
scouter_learn-0.1.10.dist-info/METADATA
scouter_learn-0.1.10.dist-info/WHEEL
scouter_learn-0.1.10.dist-info/top_level.txt
scouter_learn-0.1.10.dist-info/RECORD
